gridemissions/__init__.py
gridemissions/ampd.py
gridemissions/api.py
gridemissions/clean.py
gridemissions/configure.py
gridemissions/eia_api_v1.py
gridemissions/eia_api_v2.py
gridemissions/eia_bulk_grid_monitor.py
gridemissions/emissions.py
gridemissions/load.py
gridemissions/workflows.py
gridemissions/papers/__init__.py
gridemissions/papers/physics_informed.py
gridemissions/papers/physics_informed_cleaning_test.py
gridemissions/scripts/__init__.py
gridemissions/scripts/ampd.py
gridemissions/scripts/bulk_process.py
gridemissions/scripts/download.py
gridemissions/scripts/report.py
gridemissions/scripts/update_live_dataset.py
gridemissions/scripts/utils.py
gridemissions/viz/__init__.py
gridemissions/viz/base.py
gridemissions/viz/d3map.py
gridemissions/viz/reports.py
gridemissions-0.1.10.dist-info/LICENSE
gridemissions-0.1.10.dist-info/METADATA
gridemissions-0.1.10.dist-info/WHEEL
gridemissions-0.1.10.dist-info/entry_points.txt
gridemissions-0.1.10.dist-info/top_level.txt
gridemissions-0.1.10.dist-info/RECORD
