Metadata-Version: 2.1
Name: gridemissions
Version: 0.1.10
Requires-Python: >=3.11
License-File: LICENSE
Requires-Dist: requests
Requires-Dist: pandas >=2.1.0
Requires-Dist: matplotlib >=3.4.2
Provides-Extra: all
Requires-Dist: dask[complete] ; extra == 'all'
Requires-Dist: joblib ; extra == 'all'
Requires-Dist: cmocean ; extra == 'all'
Requires-Dist: cvxpy >=1.4.3 ; extra == 'all'
Requires-Dist: scipy >=1.10.1 ; extra == 'all'
Requires-Dist: seaborn ; extra == 'all'
Requires-Dist: syrupy ; extra == 'all'
Requires-Dist: pytest ; extra == 'all'
Requires-Dist: numpy ==1.26.4 ; extra == 'all'
